{"skeleton":{"hash":"ZGaQMUqAky5bWnj8dKq/2h+AqL0","spine":"3.8.9","x":-185,"y":-372,"width":370,"height":745,"images":"","audio":""},"bones":[{"name":"root"}],"slots":[{"name":"날아가는 붉은새_1","bone":"root","attachment":"날아가는 붉은새_10"}],"skins":[{"name":"default","attachments":{"날아가는 붉은새_1":{"날아가는 붉은새_1":{"y":0.5,"width":370,"height":745},"날아가는 붉은새_2":{"y":0.5,"width":370,"height":745},"날아가는 붉은새_3":{"y":0.5,"width":370,"height":745},"날아가는 붉은새_4":{"y":0.5,"width":370,"height":745},"날아가는 붉은새_5":{"y":0.5,"width":370,"height":745},"날아가는 붉은새_6":{"y":0.5,"width":370,"height":745},"날아가는 붉은새_7":{"y":0.5,"width":370,"height":745},"날아가는 붉은새_8":{"y":0.5,"width":370,"height":745},"날아가는 붉은새_9":{"y":0.5,"width":370,"height":745},"날아가는 붉은새_10":{"y":0.5,"width":370,"height":745}}}}],"animations":{"animation":{"slots":{"날아가는 붉은새_1":{"attachment":[{"name":"날아가는 붉은새_1"},{"time":0.1,"name":"날아가는 붉은새_2"},{"time":0.2,"name":"날아가는 붉은새_3"},{"time":0.3,"name":"날아가는 붉은새_4"},{"time":0.4,"name":"날아가는 붉은새_5"},{"time":0.5,"name":"날아가는 붉은새_6"},{"time":0.6,"name":"날아가는 붉은새_7"},{"time":0.7,"name":"날아가는 붉은새_8"},{"time":0.8,"name":"날아가는 붉은새_9"},{"time":0.9,"name":"날아가는 붉은새_10"}]}}}}}